pymesync/__init__.py
pymesync/mock_pymesync.py
pymesync/pymesync.py
pymesync-0.2.0.dist-info/DESCRIPTION.rst
pymesync-0.2.0.dist-info/METADATA
pymesync-0.2.0.dist-info/RECORD
pymesync-0.2.0.dist-info/WHEEL
pymesync-0.2.0.dist-info/metadata.json
pymesync-0.2.0.dist-info/top_level.txt
